{"ticker": "ALLE", "name": "ALLEGION PLC", "sector": "-", "industry": "Security & Protection Services", "dates": ["2021-12-31", "2022-12-31", "2023-12-31", "2024-12-31", "2025-12-31"], "revenue": [null, 3271.9, 3650.8, 3772.2, 4067.3], "gross_profit": [null, 1322.4, 1581.5, 1668.5, 1838.3], "operating_income": [null, 586.4, 715.9, 780.7, 859.5], "net_income": [null, 458.0, 540.4, 597.5, 643.8], "diluted_eps": [null, 5.19, 6.12, 6.82, 7.44], "gross_margin": [null, 40.4169, 43.3193, 44.2315, 45.1971], "operating_margin": [null, 17.9223, 19.6094, 20.6961, 21.132], "net_margin": [null, 13.998, 14.8022, 15.8396, 15.8287]}