{"ticker": "ARE", "name": "ALEXANDRIA REAL ESTATE EQUIT", "sector": "-", "industry": "REIT - Office", "dates": ["2021-12-31", "2022-12-31", "2023-12-31", "2024-12-31", "2025-12-31"], "revenue": [null, 2576.04, 2842.456, 3049.706, 2945.175], "gross_profit": [null, 1792.887, 1983.276, 2140.441, 2022.57], "operating_income": [null, 613.463, 690.449, 769.702, 555.045], "net_income": [null, 521.66, 103.639, 322.949, -1429.57], "diluted_eps": [null, 3.18, 0.54, 1.8, -8.44], "gross_margin": [null, 69.5986, 69.7733, 70.1852, 68.674], "operating_margin": [null, 23.8142, 24.2906, 25.2386, 18.8459], "net_margin": [null, 20.2505, 3.6461, 10.5895, -48.5394]}