{"ticker": "CVNA", "name": "CARVANA CO", "sector": "-", "industry": "Auto & Truck Dealerships", "dates": ["2021-12-31", "2022-12-31", "2023-12-31", "2024-12-31", "2025-12-31"], "revenue": [null, 13604.0, 10771.0, 13673.0, 20322.0], "gross_profit": [null, 1246.0, 1724.0, 2876.0, 4192.0], "operating_income": [null, -1504.0, -80.0, 990.0, 1881.0], "net_income": [null, -1587.0, 450.0, 210.0, 1407.0], "diluted_eps": [null, -3.148, 0.15, 0.318, 1.69], "gross_margin": [null, 9.1591, 16.0059, 21.0342, 20.6279], "operating_margin": [null, -11.0556, -0.7427, 7.2405, 9.256], "net_margin": [null, -11.6657, 4.1779, 1.5359, 6.9235]}