{"ticker": "HII", "name": "HUNTINGTON INGALLS INDUSTRIE", "sector": "-", "industry": "Aerospace & Defense", "dates": ["2021-12-31", "2022-12-31", "2023-12-31", "2024-12-31", "2025-12-31"], "revenue": [null, 10676.0, 11454.0, 11535.0, 12484.0], "gross_profit": [null, 1440.0, 1646.0, 1450.0, 1585.0], "operating_income": [null, 517.0, 744.0, 486.0, 611.0], "net_income": [null, 579.0, 681.0, 550.0, 605.0], "diluted_eps": [null, 14.44, 17.07, 13.96, 15.39], "gross_margin": [null, 13.4882, 14.3705, 12.5704, 12.6963], "operating_margin": [null, 4.8426, 6.4955, 4.2133, 4.8943], "net_margin": [null, 5.4234, 5.9455, 4.7681, 4.8462]}