{"ticker": "PCAR", "name": "PACCAR INC", "sector": "-", "industry": "Farm & Heavy Construction Machinery", "dates": ["2021-12-31", "2022-12-31", "2023-12-31", "2024-12-31", "2025-12-31"], "revenue": [null, 28819.7, 35127.4, 33663.8, 28444.8], "gross_profit": [null, 5226.5, 7732.6, 6709.6, 4737.5], "operating_income": [null, 3678.6, 5946.4, 4892.4, 2961.7], "net_income": [null, 3011.6, 4600.8, 4162.0, 2375.8], "diluted_eps": [null, 5.7533, 8.76, 7.9, 4.51], "gross_margin": [null, 18.1352, 22.013, 19.9312, 16.6551], "operating_margin": [null, 12.7642, 16.9281, 14.5331, 10.4121], "net_margin": [null, 10.4498, 13.0975, 12.3634, 8.3523]}