{"ticker": "TDG", "name": "TRANSDIGM GROUP INC", "sector": "-", "industry": "Aerospace & Defense", "dates": ["2021-09-30", "2022-09-30", "2023-09-30", "2024-09-30", "2025-09-30"], "revenue": [null, 5429.0, 6585.0, 7940.0, 8831.0], "gross_profit": [null, 3099.0, 3842.0, 4672.0, 5311.0], "operating_income": [null, 2215.0, 2923.0, 3577.0, 4189.0], "net_income": [null, 866.0, 1298.0, 1714.0, 2074.0], "diluted_eps": [null, 13.4, 22.03, 25.62, 32.08], "gross_margin": [null, 57.0823, 58.3447, 58.8413, 60.1404], "operating_margin": [null, 40.7994, 44.3888, 45.0504, 47.4352], "net_margin": [null, 15.9514, 19.7115, 21.5869, 23.4854]}